stare/__init__.py
stare/client.py
stare/commandline.py
stare/core.py
stare/exceptions.py
stare/utilities.py
stare/version.py
stare/models/__init__.py
stare/models/analysis.py
stare/models/paper.py
stare/settings/__init__.py
stare/settings/base.py
stare-0.1.2.dist-info/LICENSE
stare-0.1.2.dist-info/METADATA
stare-0.1.2.dist-info/WHEEL
stare-0.1.2.dist-info/entry_points.txt
stare-0.1.2.dist-info/top_level.txt
stare-0.1.2.dist-info/RECORD
